nonebot_plugin_uvdiviner/__init__.py
nonebot_plugin_uvdiviner/multilogging.py
nonebot_plugin_uvdiviner/utils.py
nonebot_plugin_uvdiviner-2.2.11.dist-info/LICENSE
nonebot_plugin_uvdiviner-2.2.11.dist-info/METADATA
nonebot_plugin_uvdiviner-2.2.11.dist-info/WHEEL
nonebot_plugin_uvdiviner-2.2.11.dist-info/top_level.txt
nonebot_plugin_uvdiviner-2.2.11.dist-info/RECORD
