Metadata-Version: 2.1
Name: nonebot-plugin-uvdiviner
Version: 2.2.11
Summary: 基于周易蓍草算法的 QQ 占卜师.
Home-page: https://gitee.com/unvisitor/nonebot-plugin-uvdiviner
Author: Night Resurgent <fu050409@163.com>
Author-email: fu050409@163.com
License: Apache-2.0
Project-URL: Bug Tracker, https://gitee.com/unvisitor/nonebot-plugin-uvdiviner/issues
Classifier: Programming Language :: Python :: 3
Classifier: License :: OSI Approved :: Apache Software License
Classifier: Operating System :: OS Independent
Requires-Python: >=3
License-File: LICENSE
Requires-Dist: nonebot2
Requires-Dist: uvdiviner
Requires-Dist: nonebot-plugin-apscheduler
